kmer_counter/__init__.py
kmer_counter/__main__.py
kmer_counter/cli.py
kmer_counter/counters.py
kmer_counter/readers.py
kmer_counter/utils.py
kmer_counter-0.2.2.dist-info/LICENSE
kmer_counter-0.2.2.dist-info/METADATA
kmer_counter-0.2.2.dist-info/WHEEL
kmer_counter-0.2.2.dist-info/entry_points.txt
kmer_counter-0.2.2.dist-info/RECORD
