Metadata-Version: 2.1
Name: kmer_counter
Version: 0.2.2
Summary: Count kmers in regions or at SNVs or at indel breakpoints.
Home-page: https://github.com/besenbacher/kmer_counter
License: MIT
Author: Søren Besenbacher
Author-email: besenbacher@clin.au.dk
Requires-Python: >=3.6,<4.0
Classifier: License :: OSI Approved :: MIT License
Classifier: Programming Language :: Python :: 3
Classifier: Programming Language :: Python :: 3.6
Classifier: Programming Language :: Python :: 3.7
Classifier: Programming Language :: Python :: 3.8
Classifier: Programming Language :: Python :: 3.9
Classifier: Programming Language :: Python :: 3.10
Classifier: Programming Language :: Python :: 3.11
Requires-Dist: argparse (>=1.4.0,<2.0.0)
Requires-Dist: py2bit (>=0.3.0,<0.4.0)
Project-URL: Repository, https://github.com/besenbacher/kmer_counter
